obpevent/__init__.py
obp_external_event-0.0.1.dist-info/LICENSE
obp_external_event-0.0.1.dist-info/METADATA
obp_external_event-0.0.1.dist-info/WHEEL
obp_external_event-0.0.1.dist-info/top_level.txt
obp_external_event-0.0.1.dist-info/RECORD
