Metadata-Version: 2.1
Name: obp-external-event
Version: 0.0.1
Summary: Trigger Metaflow executions on the Outerbounds Platform
Author: Outerbounds
Author-email: ville@outerbounds.co
License-File: LICENSE
Requires-Dist: outerbounds
